pypk/__init__.py
pypk/clear_console.py
pypk/main.py
pypk/pypi_pack.py
pypk/pypi_update.py
pypk/pypi_upload.py
pypk_up-0.0.10.dist-info/LICENSE
pypk_up-0.0.10.dist-info/METADATA
pypk_up-0.0.10.dist-info/WHEEL
pypk_up-0.0.10.dist-info/entry_points.txt
pypk_up-0.0.10.dist-info/top_level.txt
pypk_up-0.0.10.dist-info/RECORD
