Metadata-Version: 2.1
Name: pypk-up
Version: 0.0.10
Summary: 一个管理python包和上传程序的扩展工具
Home-page: 
Author: 测码范晔
Author-email: 1538379200@qq.com
License: UNKNOWN
Platform: UNKNOWN
Classifier: Programming Language :: Python :: 3
Classifier: License :: OSI Approved :: MIT License
Classifier: Operating System :: OS Independent
License-File: LICENSE
Requires-Dist: setuptools (>=60.8.1)
Requires-Dist: wheel (>=0.37.1)
Requires-Dist: twine (>=3.8.0)
Requires-Dist: pyinstaller (>=4.9)
